iolink_utils/__init__.py
iolink_utils/__version__.py
iolink_utils/exceptions.py
iolink_utils/crc/__init__.py
iolink_utils/crc/crc.py
iolink_utils/crc/crcLookupTables.py
iolink_utils/definitions/__init__.py
iolink_utils/definitions/_internal.py
iolink_utils/definitions/bitRate.py
iolink_utils/definitions/communicationChannel.py
iolink_utils/definitions/directParameterPage.py
iolink_utils/definitions/eventInfo.py
iolink_utils/definitions/eventMemory.py
iolink_utils/definitions/fsp_ioStructDescription.py
iolink_utils/definitions/iServiceNibble.py
iolink_utils/definitions/mSequenceType.py
iolink_utils/definitions/masterCommand.py
iolink_utils/definitions/onRequestDataOctetCount.py
iolink_utils/definitions/profiles.py
iolink_utils/definitions/systemCommand.py
iolink_utils/definitions/timing.py
iolink_utils/definitions/transmissionDirection.py
iolink_utils/iodd/__init__.py
iolink_utils/iodd/iodd.py
iolink_utils/iodd/iodd_fileInfo.py
iolink_utils/iodd/_internal/__init__.py
iolink_utils/iodd/_internal/iodd_documentInfo.py
iolink_utils/iodd/_internal/iodd_features.py
iolink_utils/iodd/_internal/iodd_identity.py
iolink_utils/iodd/_internal/iodd_physical_layer.py
iolink_utils/iodd/_internal/iodd_variableCollection.py
iolink_utils/iodd/_internal/iodd_xmlDoc.py
iolink_utils/messageInterpreter/__init__.py
iolink_utils/messageInterpreter/messageInterpreter.py
iolink_utils/messageInterpreter/transaction.py
iolink_utils/messageInterpreter/diagnosis/__init__.py
iolink_utils/messageInterpreter/diagnosis/commChannelDiagnosis.py
iolink_utils/messageInterpreter/diagnosis/transactionDiagnosis.py
iolink_utils/messageInterpreter/isdu/ISDU.py
iolink_utils/messageInterpreter/isdu/ISDUerrors.py
iolink_utils/messageInterpreter/isdu/ISDUflowControl.py
iolink_utils/messageInterpreter/isdu/ISDUrequests.py
iolink_utils/messageInterpreter/isdu/ISDUresponses.py
iolink_utils/messageInterpreter/isdu/__init__.py
iolink_utils/messageInterpreter/isdu/commChannelISDU.py
iolink_utils-0.1.0.dist-info/METADATA
iolink_utils-0.1.0.dist-info/WHEEL
iolink_utils-0.1.0.dist-info/licenses/LICENSE
iolink_utils-0.1.0.dist-info/RECORD
