Metadata-Version: 2.4
Name: iolink-utils
Version: 0.1.0
Summary: helper and utilities for IO-Link
Project-URL: GitHub, https://github.com/shaag7967/iolink-utils
Project-URL: Homepage, https://github.com/shaag7967/iolink-utils
Author: shaag
License:                     GNU GENERAL PUBLIC LICENSE
License-File: LICENSE
Keywords: IO-Link
Classifier: Development Status :: 5 - Production/Stable
Classifier: Programming Language :: Python :: 3.8
Classifier: Programming Language :: Python :: 3.11
Classifier: Programming Language :: Python :: 3.13
Classifier: Topic :: Software Development :: Libraries
Classifier: Topic :: Utilities
Requires-Python: >=3.8
